lazr.batchnavigator-2.1.0-py3.12-nspkg.pth
lazr/batchnavigator/__init__.py
lazr/batchnavigator/_batchnavigator.py
lazr/batchnavigator/interfaces.py
lazr/batchnavigator/docs/CONTRIBUTING.rst
lazr/batchnavigator/docs/Makefile
lazr/batchnavigator/docs/NEWS.rst
lazr/batchnavigator/docs/conf.py
lazr/batchnavigator/docs/index.rst
lazr/batchnavigator/tests/__init__.py
lazr/batchnavigator/tests/test_batchnavigator.py
lazr/batchnavigator/tests/test_docs.py
lazr/batchnavigator/tests/test_z3batching.py
lazr/batchnavigator/z3batching/COPYRIGHT.txt
lazr/batchnavigator/z3batching/LICENSE.txt
lazr/batchnavigator/z3batching/README.txt
lazr/batchnavigator/z3batching/__init__.py
lazr/batchnavigator/z3batching/batch.py
lazr/batchnavigator/z3batching/interfaces.py
lazr.batchnavigator-2.1.0.dist-info/COPYING.txt
lazr.batchnavigator-2.1.0.dist-info/METADATA
lazr.batchnavigator-2.1.0.dist-info/WHEEL
lazr.batchnavigator-2.1.0.dist-info/namespace_packages.txt
lazr.batchnavigator-2.1.0.dist-info/top_level.txt
lazr.batchnavigator-2.1.0.dist-info/RECORD
