Metadata-Version: 2.1
Name: lazr.batchnavigator
Version: 2.1.0
Summary: A helper to navigate batched results in a web page.
Home-page: https://launchpad.net/lazr.batchnavigator
Download-URL: https://launchpad.net/lazr.batchnavigator/+download
Maintainer: LAZR Developers
Maintainer-email: lazr-users@lists.launchpad.net
License: LGPL v3
Project-URL: Source, https://code.launchpad.net/lazr.batchnavigator
Project-URL: Issue Tracker, https://bugs.launchpad.net/lazr.batchnavigator
Project-URL: Documentation, https://lazrbatchnavigator.readthedocs.io/en/latest/
Classifier: Development Status :: 5 - Production/Stable
Classifier: Intended Audience :: Developers
Classifier: License :: OSI Approved :: GNU Library or Lesser General Public License (LGPL)
Classifier: Operating System :: OS Independent
Classifier: Programming Language :: Python
Classifier: Programming Language :: Python :: 3
Classifier: Programming Language :: Python :: 3.8
Classifier: Programming Language :: Python :: 3.9
Classifier: Programming Language :: Python :: 3.10
Classifier: Programming Language :: Python :: 3.11
Classifier: Programming Language :: Python :: 3.12
Classifier: Programming Language :: Python :: 3.13
Requires-Python: >=3.8
License-File: COPYING.txt
Requires-Dist: setuptools
Requires-Dist: six
Requires-Dist: zope.cachedescriptors
Requires-Dist: zope.interface>=3.6.0
Provides-Extra: docs
Requires-Dist: Sphinx; extra == "docs"
Provides-Extra: test
Requires-Dist: testtools; extra == "test"
Requires-Dist: zope.publisher; extra == "test"
Requires-Dist: zope.testrunner; extra == "test"
